LICENSE
MANIFEST.in
README.md
requirements.txt
setup.py
assets/__init__.py
examples/__init__.py
examples/example_account.py
examples/example_atomic_swap.py
examples/example_block_info.py
examples/example_certificate.py
examples/example_keys.py
examples/example_pubkey.py
examples/example_token.py
examples/example_ws_events.py
remme/__init__.py
remme/account.py
remme/api.py
remme/atomic_swap.py
remme/blockchain_info.py
remme/certificate.py
remme/keys.py
remme/node_management.py
remme/public_key_storage.py
remme/remme.py
remme/token.py
remme/transaction_service.py
remme/utils.py
remme/websocket.py
remme/websocket_events.py
remme.egg-info/PKG-INFO
remme.egg-info/SOURCES.txt
remme.egg-info/dependency_links.txt
remme.egg-info/requires.txt
remme.egg-info/top_level.txt
remme/models/__init__.py
remme/models/account/__init__.py
remme/models/account/account_type.py
remme/models/atomic_swap/__init__.py
remme/models/atomic_swap/swap_init_dto.py
remme/models/blockchain_info/__init__.py
remme/models/blockchain_info/block_info.py
remme/models/blockchain_info/network_status.py
remme/models/blockchain_info/query.py
remme/models/certificate/__init__.py
remme/models/certificate/certificate_transaction_response.py
remme/models/certificate/x509_certificate_builder.py
remme/models/general/__init__.py
remme/models/general/batch_status.py
remme/models/general/methods.py
remme/models/general/patterns.py
remme/models/interfaces/__init__.py
remme/models/interfaces/api.py
remme/models/interfaces/atomic_swap.py
remme/models/interfaces/blockchain_info.py
remme/models/interfaces/certificate.py
remme/models/interfaces/keys.py
remme/models/interfaces/node_management.py
remme/models/interfaces/public_key_storage.py
remme/models/interfaces/token.py
remme/models/interfaces/transaction_service.py
remme/models/interfaces/websocket.py
remme/models/interfaces/websocket_events.py
remme/models/keys/__init__.py
remme/models/keys/ecdsa.py
remme/models/keys/eddsa.py
remme/models/keys/key_dto.py
remme/models/keys/key_type.py
remme/models/keys/rsa.py
remme/models/keys/rsa_signature_padding.py
remme/models/node_management/__init__.py
