Metadata-Version: 2.1
Name: remme
Version: 1.1.1
Summary: Python integration library for REMChain.
Home-page: https://github.com/Remmeauth/remme-client-python
Author: Remme
License: Apache License 2.0
Platform: UNKNOWN
Classifier: Operating System :: OS Independent
Classifier: License :: OSI Approved :: Apache Software License
Classifier: Programming Language :: Python :: 3.6
Classifier: Programming Language :: Python :: 3.7
